{
  "title": "Greenmantle",
  "authors": "Buchan, John, 1875-1940",
  "year": 1916,
  "genre": "Mystery",
  "slug": "greenmantle",
  "length": 545633,
  "original_metadata": {
    "language": "en",
    "text_id": 559,
    "title": "Greenmantle",
    "issued": "1996-06-01 00:00:00",
    "authors": "Buchan, John, 1875-1940",
    "subjects": "World War, 1914-1918 -- Fiction; War stories; Spy stories; Hannay, Richard (Fictitious character) -- Fiction; Intelligence service -- Great Britain -- Fiction",
    "locc": "PR",
    "bookshelves": "World War I; Adventure; Mystery Fiction; Movie Books"
  }
}