{
  "id": 15954,
  "title": "Mary Jane\u2014Her Visit",
  "authors": "Judson, Clara Ingram, 1879-1960; White, Frances [Illustrator]",
  "year": 1918,
  "genre": "Fiction",
  "slug": "mary-jane-her-visit",
  "length": 162664,
  "original_metadata": {
    "language": "en",
    "text_id": 15954,
    "title": "Mary Jane\u2014Her Visit",
    "issued": "2005-05-31 00:00:00",
    "authors": "Judson, Clara Ingram, 1879-1960; White, Frances [Illustrator]",
    "subjects": "Girls -- Juvenile fiction; Country life -- Juvenile fiction; Grandparents -- Juvenile fiction",
    "locc": "PZ",
    "bookshelves": ""
  }
}