{
  "id": 14829,
  "title": "Our Holidays\nTheir Meaning and Spirit; retold from St. Nicholas",
  "authors": "Various",
  "year": 1905,
  "genre": "History",
  "slug": "our-holidays-their-meaning-and-spirit-retold-from-st-nicholas",
  "length": 148831,
  "original_metadata": {
    "language": "en",
    "text_id": 14829,
    "title": "Our Holidays\nTheir Meaning and Spirit; retold from St. Nicholas",
    "issued": "2005-01-29 00:00:00",
    "authors": "Various",
    "subjects": "Holidays -- Juvenile literature; Festivals -- Juvenile literature",
    "locc": "PZ",
    "bookshelves": ""
  }
}