{
  "title": "Robin Hood",
  "authors": "McSpadden, J. Walker (Joseph Walker), 1874-1960",
  "year": 1923,
  "genre": "Fantasy",
  "slug": "robin-hood",
  "length": 391434,
  "original_metadata": {
    "language": "en",
    "text_id": 832,
    "title": "Robin Hood",
    "issued": "2006-01-21 00:00:00",
    "authors": "McSpadden, J. Walker (Joseph Walker), 1874-1960",
    "subjects": "Folklore -- England; Robin Hood (Legendary character) -- Legends",
    "locc": "PZ",
    "bookshelves": "Fantasy"
  }
}