{
  "id": 15578,
  "title": "The Miracle Man",
  "authors": "Packard, Frank L. (Frank Lucius), 1877-1942",
  "year": 1914,
  "genre": "Fiction",
  "slug": "the-miracle-man",
  "length": 388536,
  "original_metadata": {
    "language": "en",
    "text_id": 15578,
    "title": "The Miracle Man",
    "issued": "2005-04-07 00:00:00",
    "authors": "Packard, Frank L. (Frank Lucius), 1877-1942",
    "subjects": "Maine -- Fiction; People with disabilities -- Fiction; Poor -- Fiction; Canadian fiction",
    "locc": "PS",
    "bookshelves": ""
  }
}